pyedictor/__init__.py
pyedictor/cli.py
pyedictor/sqlite.py
pyedictor/util.py
pyedictor-1.0.0.dist-info/LICENSE
pyedictor-1.0.0.dist-info/METADATA
pyedictor-1.0.0.dist-info/WHEEL
pyedictor-1.0.0.dist-info/top_level.txt
pyedictor-1.0.0.dist-info/RECORD
