Metadata-Version: 2.1
Name: pyedictor
Version: 1.0.0
License-File: LICENSE
Requires-Dist: edictor[lingpy]
